{
    "BUTTONS": {
        "ACCESS": "Zugriffsstatus",
        "ACTION": "Aktion",
        "ADD": "Hinzufügen",
        "ADDDEVICE": "Geräte hinzufügen",
        "APPLY": "Anwenden",
        "BIG": "Groß",
        "CANCEL": "Abbrechen",
        "CLASSES": "Klassen",
        "CLOSE": "Schließen",
        "CONFIRM": "Abschließen",
        "COPYFILE": "Datei verteilen",
        "COPYTEMP": "Template verteilen",
        "CREATEANN": "Neue Benachrichtigung",
        "CREATECAT": "Neue Kategorie",
        "CREATECONFIG": "ISO erstellen",
        "CREATEFAQ": "Neue FAQ",
        "CSVEXP": "CSV Export",
        "DELETE": "Löschen",
        "DELETEPROFILE": "Profil löschen",
        "DETAILS": "Details",
        "DISINTERNET": "Internet",
        "DISLOGIN": "Anmeldung",
        "DOWNLOAD": "Herunterladen",
	"DOWNLOADVPNCONFIG" : "VPN-Konfiguration laden",
	"DOWNLOADVPNEXEC" : "VPN-Installer laden",
        "EDIT": "Bearbeiten",
        "EDITMYPW": "Passwort ändern",
        "FREE": "Entsperren",
        "GROUPS": "Gruppen",
        "IMAGE": "Imagen",
        "IMGHWCONF": "Imagen",
        "IMPORT": "Importieren",
        "IMPORTDEV": "Geräte importieren",
        "IMPORTGROUP": "Gruppen importieren",
        "IMPORTROOM": "Räume importieren",
        "INSTALLSTATUS": "Installationen",
	"KEYS" : "Schlüssel",
        "LIST": "Liste",
        "LOGOUT": "Abmelden",
        "LOCK": "Sperren",
        "MEDIUM": "Mittel",
        "MULTICAST": "Multicast Klonen",
        "NOTES": "Notizen",
        "OK": "OK",
        "RESTART": "Restart",
        "REBOOT": "Neustarten",
        "REMOVE": "Entfernen",
        "RESET": "Zurücksetzen",
        "RESTART": "Neustarten",
        "RESYNC": "Erneut synchronisieren",
        "ROLES": "Rollen",
        "ROOMS": "Räume",
        "ROOMSIZE": "Anzeigegröße",
        "SEARCH" : "Suchen",
        "SELECTROOM": "Raum wählen",
        "SELECT": "Auswählen",
        "SEND": "Senden",
        "SET": "Setzen",
        "SETACCESS": "Zugriff",
        "SETADD": "Installset verteilen",
        "SETASMASTER": "Master",
        "SETAVAI": "Verfügbar",
        "SETDEF": "Standard",
        "SETDHCP": "DHCP Parameter setzten",
        "SETFSQUOTA": "Filesystemquota setzten",
        "SETHWOFROOM": "HWConf des Raumes setzten",
        "SETMSQUOTA": "Mailsystemquota setzten",
        "SETPRINTER": "Drucker hinzufügen",
        "SETPW": "Passwort ändern",
        "SETWPW": "Workstationuser-Passwort setzen",
        "SHEDULE": "Zugriffszeitplan",
        "SHOWLIC": "Lizenz",
        "SHUTDOWN": "Herunterfahren",
        "SMALL": "Klein",
        "STARTSHARE": "Starten",
        "STATUS": "Details",
        "SYNC": "Synchronisieren",
        "SUBMIT": "Anlegen",
        "TYPES": "Art",
        "UPDATES": "Aktualisierungen",
        "UPDATE": "Aktualisieren",
        "WAKE": "Wecken",
        "WORKGROUPS": "AGs",
        "WRITECOFIG": "Auswahl Imagen"
    },
    "COLLECT": {
        "CLEANUPDIR": "Import und Export aufräumen",
        "PROJCETNAME": "Projektname",
        "PROJECTNAME": "Projektname",
        "SORTINDIRS": "Pro Benutzer ein Verzeichnis erstellen",
        "TITLE": "Dateien einsammeln"
    },
    "CONFIGURATION": {
        "BACKUP": "Backup",
        "BASIC": "Grundkonfiguration",
        "SETTINGS": "Einstellungen",
        "TITLE": "Globale Konfiguration"
    },
    "DIALOG": {
        "MUSTCHANGE": "Benutzer muss das Passwort ändern",
	"RESPONSE": "Rückmeldungen",
        "SETPWQ": "Passwort für Benutzer setzen.",
        "SETPWWORK": "Passwort für Workstationsuser setzen."
    },
    "EDU": {
        "ALLOWDIRECT": "Direkter Internetzugang",
        "ALLOWLOGIN": "Anmeldung erlaubt",
        "ALLOWPRINT": "Drucken erlaubt",
        "CLEANUPDIR": "Exportordner Aufräumen",
        "COLLECT": "Dateien einsammeln",
        "COLLTITLE": "Dateien einsammeln",
        "CPROJCETNAME": "Projektname",
        "CSORTINDIRS": "Verzeichnis pro Benutzer anlegen",
        "DEVICEPLACE": "Platz",
        "DEVICEROW": "Reihe",
        "DEVICESINROOM": "Geräte",
        "DRAGHERE": "Hier her bewegen",
        "LOGGEDINUSERS": "Angemeldete Benutzer",
        "PORTAL": "Portal",
        "PROXYACT": "Proxy an",
        "ROOM": "Raum",
        "ROOMSELECTTITLE": "Zu steuernden Raum wählen!",
        "SELECTEDROOM": "Gewählter Raum",
        "SELECTMYROOM": "Auswählen",
        "SELECTUSER": "Benutzer wählen",
        "SHARE": "Dateie verteilen",
        "STUDENTSONLY": "Nur Schüler",
        "TITLE": "Raumüberwachnung",
        "UTITLE": "Datei verteilen"
    },
    "ERRORS":{
	"BIRTHDAYREQ": "Geburtstag fehlt!",
	"DESCRERR" : "Beschreibung fehlt!",
	"GIVENNAME" : "Vornamen fehlt!",
	"HWCERR" : "Hardwarekonfiguration fehlt!.",
	"MAC" : "MAC-Adresse fehlt!",
	"NAME": "Name fehlt!",
	"PATTERNMAC": "MAC-Adresse ungültig!",
	"SURNAME" : "Nachname fehlt!",
	"PWNMATCH" : "Passwörter stimmen nicht überein"
    },
    "PLACEHOLDERS": {
	"ACTION" : "Aktion",
	"ACTIVE" : "Wird ausgeführt",
        "ADDCATEGORY": "Kategorie hinzufügen",
        "ADMINPW": "Adminpasswort",
        "ALIAS": "E-Mail-Aliases",
        "ALLCLASSES": "Alle Klassen",
        "ANONDHCP": "AnnonyDHCP",
        "BIRTHDAY": "Geburtstag",
        "CATTYPE": "Type",
        "CEPHALIXPW": "Cephalixpasswort",
        "CHANGEPW": "Passwort muss gändert werden.",
	"CLASSES": "Klassen",
        "CLEANCLASSDIRS": "Klassenverzeichnis leeren",
        "DESCR": "Beschreibung",
        "DEST": "Ziel",
	"DEVICE": "Gerät",
        "DIRECTORY": "Pfad",
        "DOMAIN": "Domäne",
        "DROPFILE": "Datei hierher ziehen",
        "EDIT": "Bearbeiten",
        "EMAIL": "EMailadresse",
	"ENABLED" : "Aktiviert",
        "ENTERTXT": "Text eintragen",
        "EXECUTE": "Ausführen",
	"EXTPORT": "Außenport",
        "FALSE": "Nein",
        "FIRSTROOM": "Ersterraum",
        "FRI": "Fr",
        "FULL": "Vollständig",
        "FULLNAME": "Name",
        "GIVENNAME": "Vorname",
        "GNSNBD": "Voller Name + Geburtstag",
        "GTWSCHOOL": "Gateway (intern)",
        "GWTRNET": "Gateway (extern)",
        "HOLIDAY": "Feiertags",
        "IDENTIFIER": "Identifikator",
        "INSTITUTENAME": "Institutname",
        "IP": "IP-Adresse",
        "IPADMIN": "Server",
        "IPBACKUP": "Backupserver",
        "IPMAIL": "Mailserver",
        "IPPRINT": "Printserver",
        "IPPROXY": "Proxy",
        "IPTRNET": "IP (extern)",
        "IPVPN": "VerbindungsIP",
        "ISSUE": "Thema",
        "KEYWORD": "Schlüsselwörte",
        "LANG": "Sprache",
        "LICCOUNT": "Anzahl",
        "LICKEY": "Lizenzschlüssel",
        "LICTYPE": "Lizenztyp",
        "LOCALITY": "Ort",
        "MAC": "MAC-Adresse",
        "MODE": "Mode",
        "MON": "Mo",
        "MUSTCHANGE": "Passwort ändern",
        "NAME": "Name",
        "NETMASK": "Netzwerkmaske",
        "NETWORK": "Netzwerk (intern)",
	"NEXT": "Nächste standard Werte",
        "NMSERVERNET": "Servernetz",
        "NMTRNET": "Netzwerkmaske Transportnetz",
        "PASSWORD": "Passwort",
        "PHONE": "Telefonnumer",
        "PORT": "Port",
        "PRODUCT": "Produkt",
        "PROT": "Protokoll",
        "REGCODE": "Registrierungscode",
        "RESETPW": "Passwort zurücksetzten",
        "ROLE": "Role",
        "ROOM": "Raum",
        "SAT": "Sa",
        "SEARCH": "Suchen",
        "SELECT": "Wählen",
        "SELECTFILE": "Date wählen",
        "SELECTHWCONFIG": "HWConfig wählen",
	"SELECTOS" : "Betriebssystem wählen",
        "SELECTROOM": "Raum wählen",
        "SUBJECT": "Betreff",
        "SUN": "So",
        "SURNAME": "Nachname",
        "TARGET": "Quelle",
        "TESTIMPORT": "Testimport",
        "TITLE": "Titel",
        "THU": "Do",
        "TIMEPICK": "Zeitpunkt",
        "TRUE": "Ja",
        "TUE": "Di",
        "TYPE": "Art",
        "USERNAME": "Benutzername",
        "UUID": "Kennung (uuid)",
        "VALIDFROM": "Gültig von",
        "VALIDUNTIL": "Gültig bis",
        "WED": "Mi"
    },
    "TOOLTIP": {
        "BLOCKDEVICE": "Sperren",
        "LOGOFF": "Abmelden",
        "RESTART": "Neu starten",
        "SHUTDOWN": "Ausschalten",
        "UNBLOCK": "Entsperren"
    },
    "SYSTEM": {
	"ADDONS"   : "Addons",
	"DASHBOARD": "Systemübersicht",
	"SERVICES" : "Dienste",
	"STATUS" : "Systemstatus",
	"OVERVIEW" : "Serverstatus"
    },
    "students": "Schüler",
    "teachers": "Lehrer",
    "sysadmins" : "Sysadmins",
    "administration": "Verwaltung",
    "workstations" : "Workstation",
    "work" : "Berufsschule",
    "global" : "Gesamtschule",
    "primary": "Grundschule",
    "gymnasium" : "Gymnasium",
    "secondary" : "Haupt-/Mittelschule",
    "secondary_school" : "Sekundarschule",
    "real" : "Realschule",
    "special" : "Sonderschule",
    "other" : "Sonstige"
}
